llama/__init__.py
llama/lemma/__init__.py
llama/lemma/bemma.py
llama/lima/__init__.py
llama/lima/bima.py
llama/rancher.py
llama_and_llama-0.2.0.dist-info/WHEEL
llama_and_llama-0.2.0.dist-info/METADATA
llama_and_llama-0.2.0.dist-info/RECORD
