Metadata-Version: 2.1
Name: llama-and-llama
Version: 0.2.0
Summary: LIMA
Author: asdftoger
Author-email: asdftoger@gmail.com
Requires-Python: >=3.9,<4.0
Classifier: Programming Language :: Python :: 3
Classifier: Programming Language :: Python :: 3.9
Classifier: Programming Language :: Python :: 3.10
Classifier: Programming Language :: Python :: 3.11
